[{"sendersId":1,"recipientName":"John Doe","recipientAccountNumber":7725180923,"amount":2500,"description":"","transactionType":"Credit","transactionMethod":"Transfer","transactionStatus":"successful","sendersName":"John Doe","sendersAccountNumber":7725180923,"userId":1,"availableBalance":2500},{"sendersId":1,"recipientName":"John Doe","recipientAccountNumber":7725180923,"amount":2500,"description":"","transactionType":"Credit","transactionMethod":"Transfer","transactionStatus":"successful","sendersName":"John Doe","sendersAccountNumber":7725180923,"userId":1,"availableBalance":2500}]